pytest_zebrunner/__init__.py
pytest_zebrunner/api/__init__.py
pytest_zebrunner/api/client.py
pytest_zebrunner/api/models.py
pytest_zebrunner/attachments.py
pytest_zebrunner/ci_loaders.py
pytest_zebrunner/context.py
pytest_zebrunner/current_test.py
pytest_zebrunner/current_test_run.py
pytest_zebrunner/errors.py
pytest_zebrunner/hooks.py
pytest_zebrunner/plugin.py
pytest_zebrunner/reporting_service.py
pytest_zebrunner/selenium_integration.py
pytest_zebrunner/settings.py
pytest_zebrunner/tcm/__init__.py
pytest_zebrunner/tcm/base.py
pytest_zebrunner/tcm/test_rail.py
pytest_zebrunner/tcm/xray.py
pytest_zebrunner/tcm/zebrunner.py
pytest_zebrunner/tcm/zephyr.py
pytest_zebrunner/utils.py
pytest_zebrunner/zebrunner_logging.py
pytest_zebrunner-1.6.2.dist-info/LICENSE
pytest_zebrunner-1.6.2.dist-info/METADATA
pytest_zebrunner-1.6.2.dist-info/WHEEL
pytest_zebrunner-1.6.2.dist-info/entry_points.txt
pytest_zebrunner-1.6.2.dist-info/RECORD
