Metadata-Version: 2.1
Name: pytest-zebrunner
Version: 1.6.2
Summary: Pytest connector for Zebrunner reporting
Home-page: https://zebrunner.com/documentation/agents/pytest
License: Apache
Keywords: automation,zebrunner,testing
Author: Anatoliy Platonov
Author-email: p4m.dev@gmail.com
Requires-Python: >=3.8,<4.0
Classifier: Development Status :: 5 - Production/Stable
Classifier: Framework :: Pytest
Classifier: Intended Audience :: Developers
Classifier: Intended Audience :: Information Technology
Classifier: Intended Audience :: System Administrators
Classifier: License :: OSI Approved :: Apache Software License
Classifier: License :: Other/Proprietary License
Classifier: Operating System :: OS Independent
Classifier: Programming Language :: Python :: 3
Classifier: Programming Language :: Python :: 3.8
Classifier: Programming Language :: Python :: 3.9
Classifier: Programming Language :: Python :: 3.10
Classifier: Programming Language :: Python :: 3.11
Classifier: Programming Language :: Python :: 3.12
Classifier: Topic :: Internet
Classifier: Topic :: Software Development
Classifier: Topic :: Software Development :: Libraries
Classifier: Topic :: Software Development :: Libraries :: Application Frameworks
Classifier: Topic :: Software Development :: Libraries :: Python Modules
Requires-Dist: PyYAML (>=6.0.1,<7.0.0)
Requires-Dist: httpx (>=0.25.0,<0.26.0)
Requires-Dist: pydantic (>=1.0,<2.0)
Requires-Dist: pytest (>=4.5.0)
Requires-Dist: python-dotenv (>=0.10)
Project-URL: Repository, https://github.com/zebrunner/python-agent-pytest
